lrclib/__init__.py
lrclib/api.py
lrclib/cryptographic_challenge_solver.py
lrclib/exceptions.py
lrclib/models.py
lrclibapi-0.2.2.dist-info/METADATA
lrclibapi-0.2.2.dist-info/WHEEL
lrclibapi-0.2.2.dist-info/RECORD
