Metadata-Version: 2.1
Name: lrclibapi
Version: 0.2.2
Summary: python wrapper for the lrclib.net api
Home-page: https://github.com/Dr-Blank/lrclibapi
License: MIT
Keywords: lrclib,lrclib.net,lrclib.net api,lrclib.net python,lrclib.net python api,lrclib.net python wrapper,synced lyrics,synced lyrics api,synced lyrics python
Author: Dr-Blank
Author-email: 64108942+Dr-Blank@users.noreply.github.com
Requires-Python: >=3.8.10,<4.0.0
Classifier: Development Status :: 4 - Beta
Classifier: Intended Audience :: Developers
Classifier: License :: OSI Approved :: MIT License
Classifier: Programming Language :: Python :: 3
Classifier: Programming Language :: Python :: 3.9
Classifier: Programming Language :: Python :: 3.10
Classifier: Programming Language :: Python :: 3.11
Classifier: Topic :: Software Development :: Libraries :: Python Modules
Classifier: Topic :: Utilities
Requires-Dist: requests (>=2.31.0,<3.0.0)
Project-URL: Repository, https://github.com/Dr-Blank/lrclibapi
